Metadata-Version: 2.1
Name: vcstool-p-utils
Version: 0.0.2
Summary: A demo package.
